{
	"$schema": "http://schema.management.azure.com/schemas/2015-01-01/deploymentTemplate.json#",
	"contentVersion": "1.0.0.0",
	"parameters": {
		"factoryName": {
			"type": "string",
			"metadata": "Data Factory name",
			"defaultValue": "OptyADF"
		}
	},
	"variables": {
		"factoryId": "[concat('Microsoft.DataFactory/factories/', parameters('factoryName'))]"
	},
	"resources": [
		{
			"name": "[concat(parameters('factoryName'), '/Producao Medica Itaigara')]",
			"type": "Microsoft.DataFactory/factories/pipelines",
			"apiVersion": "2018-06-01",
			"properties": {
				"description": "Pipeline desenvolvido para extração de informações de produção medica das unidades com o sistema Tasy e Smart.",
				"activities": [
					{
						"name": "Wait1",
						"type": "Wait",
						"dependsOn": [],
						"userProperties": [],
						"typeProperties": {
							"waitTimeInSeconds": 1
						}
					},
					{
						"name": "Producao Procedimentos DH",
						"type": "Copy",
						"dependsOn": [
							{
								"activity": "Wait1",
								"dependencyConditions": [
									"Succeeded"
								]
							}
						],
						"policy": {
							"timeout": "7.00:00:00",
							"retry": 0,
							"retryIntervalInSeconds": 30,
							"secureOutput": false,
							"secureInput": false
						},
						"userProperties": [],
						"typeProperties": {
							"source": {
								"type": "SqlServerSource",
								"sqlReaderQuery": "    select\n        'Smart Itaigara' as BASE\n        ,EMP_CGC as CNPJ\n        ,gcc_descr as MARCA\n        ,smm_dthr_alter as DT_ATUALIZACAO \n        ,convert(varchar,osm_serie) + convert(varchar,osm_num) as NR_ATENDIMENTO --duvida\n        ,osm_dthr as DT_ENTRADA\n        ,convert(varchar,osm_serie) + convert(varchar,osm_num) as NR_INTERNO_CONTA --duvida\n        ,osm_pac as CD_PESSOA_FISICA\n        ,pac_nasc as DT_NASCIMENTO\n        ,pac_numcpf as NR_CPF\n        ,pac_sexo as IE_SEXO\n        ,pac_cep as NR_CEP\n        ,case when isnumeric(pac_cid) = 1 then (select cde_nome from cde where cde_cod = pac_cid)\n        else pac_cid end as DS_CIDADE\n        ,pac_nome as DS_PESSOA_FISICA\n        ,cnv_cod as CD_CONVENIO\n        ,cnv_nome as DS_CONVENIO\n        ,psv_exe.psv_cod as CD_MEDICO_EXECUTOR\n        ,psv_exe.psv_apel as DS_MEDICO_EXECUTOR\n        ,psv_req.psv_cod as CD_MEDICO_REQUISITANTE\n        ,psv_req.psv_apel as DS_MEDICO_REQUISITANTE\n        ,isnull(tab_padrao,0) as IE_ORIGEM_PROCEDIMENTO\n        ,smm_cod as CD_PROCEDIMENTO\n        ,smk_rot as DS_PROCEDIMENTO\n        ,case ctf_categ \n            when 'C' then 'Consulta'\n            when 'E' then 'Exames'\n            when 'R' then 'Cirurgia'\n            when 'T' then 'Taxas'\n            when 'A' then 'Terapia'\n            when 'O' then 'Outras'\n            when 'M' then 'Materiais'\n            when 'S' then 'Materiais Especiais'\n            when 'N' then 'Medicamentos'\n            when 'G' then 'Gases'\n            when 'O' then 'Outros'\n        end as DS_CLASSIFICACAO\n        ,smm_qt as QT_PROCEDIMENTO\n        ,smm_vlr + isnull(smm_ajuste_vlr,0) as VL_PROCEDIMENTO\n        ,case \n            when smm_fat_serie is not null then 2\n        else 1 end AS IE_STATUS_ACERTO\n        ,case \n            when smm_fat_serie is not null then 'Definitivo'\n        else 'Provisório' end as STATUS_CONTA\n        ,0 as CD_TUSS,\n        0 as NR_SEQ_PROC_INTERNO\n    from \n        osm\n        inner join smm on (smm_osm_serie = osm_serie and smm_osm = osm_num)\n        inner join str str_osm on (str_osm.str_cod = osm_str)\n        inner join str str_emp on (str_osm.str_str_cod = str_emp.str_cod)\n        inner join pac on (pac_reg = osm_pac)inner join cnv on (cnv_cod = osm_cnv)\n        inner join psv psv_exe on (psv_exe.psv_cod = smm_med)\n        inner join psv psv_req on (psv_req.psv_cod = smm_med)\n        inner join smk on (smk_cod = smm_cod and smk_tipo = smm_tpcod)\n        inner join gcc on (str_emp.str_cod = gcc_cod)\n        \n        inner join emp ON (emp_cod = str_emp.str_emp_cod)\n\n        inner join ctf on (ctf_cod = smk_ctf and ctf_tipo = smk_tipo)\n        left outer join tab on (tab_cod = smm_tab_cod)\n    where \n        1 = 1\n        and convert(varchar(10), osm_dthr, 103) = convert(varchar(10), getdate(), 103)\nand osm_dthr between GETDATE() - 730 and GETDATE()",
								"queryTimeout": "02:00:00",
								"partitionOption": "None"
							},
							"sink": {
								"type": "AzureSqlSink"
							},
							"enableStaging": false
						},
						"inputs": [
							{
								"referenceName": "SMART_ITAIGARA_PrdDataSet",
								"type": "DatasetReference",
								"parameters": {}
							}
						],
						"outputs": [
							{
								"referenceName": "AZ_SQL_TB_Unidade_Producao_Medica",
								"type": "DatasetReference",
								"parameters": {}
							}
						]
					},
					{
						"name": "Convenios",
						"type": "Copy",
						"dependsOn": [
							{
								"activity": "Wait1",
								"dependencyConditions": [
									"Succeeded"
								]
							}
						],
						"policy": {
							"timeout": "7.00:00:00",
							"retry": 0,
							"retryIntervalInSeconds": 30,
							"secureOutput": false,
							"secureInput": false
						},
						"userProperties": [],
						"typeProperties": {
							"source": {
								"type": "SqlServerSource",
								"sqlReaderQuery": "select cnv_cod AS CD_CONVENIO, cnv.cnv_nome AS DS_CONVENIO, gcc.gcc_cod AS CD_ESTABELECIMENTO, emp.emp_cgc AS CNPJ\nfrom cnv,\n     gcc,\n     str,\n     emp\nwhere gcc.gcc_str_cod = str_cod\nand str_emp_cod = emp_cod\nand emp_cgc <> '-'\nand cnv_cod <> '999'\nand cnv_stat = 'A'",
								"queryTimeout": "02:00:00",
								"partitionOption": "None"
							},
							"sink": {
								"type": "AzureSqlSink"
							},
							"enableStaging": false
						},
						"inputs": [
							{
								"referenceName": "SMART_ITAIGARA_PrdDataSet",
								"type": "DatasetReference",
								"parameters": {}
							}
						],
						"outputs": [
							{
								"referenceName": "AZ_SQL_TB_Convenio",
								"type": "DatasetReference",
								"parameters": {}
							}
						]
					},
					{
						"name": "Setor",
						"type": "Copy",
						"dependsOn": [
							{
								"activity": "Wait1",
								"dependencyConditions": [
									"Succeeded"
								]
							}
						],
						"policy": {
							"timeout": "7.00:00:00",
							"retry": 0,
							"retryIntervalInSeconds": 30,
							"secureOutput": false,
							"secureInput": false
						},
						"userProperties": [],
						"typeProperties": {
							"source": {
								"type": "SqlServerSource",
								"sqlReaderQuery": "SELECT STR_COD AS CD_SETOR_ATENDIMENTO, \nSTR_NOME AS DS_SETOR_ATENDIMENTO, \nEMP_CGC AS CNPJ\nFROM STR, EMP\nWHERE STR_EMP_COD = EMP_COD\nAND EMP_CGC <> '-'\nAND STR_COD <> '999'",
								"queryTimeout": "02:00:00",
								"partitionOption": "None"
							},
							"sink": {
								"type": "AzureSqlSink"
							},
							"enableStaging": false
						},
						"inputs": [
							{
								"referenceName": "SMART_ITAIGARA_PrdDataSet",
								"type": "DatasetReference",
								"parameters": {}
							}
						],
						"outputs": [
							{
								"referenceName": "AZ_SQL_TB_Setor",
								"type": "DatasetReference",
								"parameters": {}
							}
						]
					},
					{
						"name": "Execute Oftamoclin",
						"type": "ExecutePipeline",
						"dependsOn": [
							{
								"activity": "Producao Procedimentos DH",
								"dependencyConditions": [
									"Succeeded"
								]
							},
							{
								"activity": "Convenios",
								"dependencyConditions": [
									"Succeeded"
								]
							},
							{
								"activity": "Setor",
								"dependencyConditions": [
									"Succeeded"
								]
							}
						],
						"userProperties": [],
						"typeProperties": {
							"pipeline": {
								"referenceName": "Producao Medica Oftalmoclin",
								"type": "PipelineReference"
							},
							"waitOnCompletion": true,
							"parameters": {}
						}
					}
				],
				"folder": {
					"name": "Produção Médica CSI"
				},
				"annotations": []
			},
			"dependsOn": []
		},
		{
			"name": "[concat(parameters('factoryName'), '/Geral Atendimentos INOB - Smart')]",
			"type": "Microsoft.DataFactory/factories/pipelines",
			"apiVersion": "2018-06-01",
			"properties": {
				"description": "Alimenta as informações das tabelas:\n\nAtendimento_ Unidade \nAgendamento_Unidade\nUsuarios_Unidade\nConsultas_Unidade\nAgendas Unidade\n\nPara extração de relatórios do call center.",
				"activities": [
					{
						"name": "Wait1",
						"type": "Wait",
						"dependsOn": [],
						"userProperties": [],
						"typeProperties": {
							"waitTimeInSeconds": 1
						}
					},
					{
						"name": "Atendimento INOB",
						"type": "Copy",
						"dependsOn": [
							{
								"activity": "Wait1",
								"dependencyConditions": [
									"Succeeded"
								]
							}
						],
						"policy": {
							"timeout": "7.00:00:00",
							"retry": 0,
							"retryIntervalInSeconds": 30,
							"secureOutput": false,
							"secureInput": false
						},
						"userProperties": [],
						"typeProperties": {
							"source": {
								"type": "SqlServerSource",
								"sqlReaderQuery": "SELECT DISTINCT pac_reg AS CD_PESSOA_FISICA\n    , rtrim(ltrim(pac_nome)) AS NM_PESSOA_FISICA\n    , convert(CHAR(10), osm_dthr, 121) AS DT_ENTRADA\n    , LEFT(CONVERT(VARCHAR(12), osm_dthr, 114),8) AS HR_ENTRADA\n    , smm_med AS NM_MEDICO\n    , osm_cnv AS CD_CONVENIO\n    , cnv_nome AS DS_CONVENIO\n    , convert(VARCHAR, (convert(VARCHAR, osm_serie) + convert(VARCHAR, osm_num))) AS NR_ATENDIMENTO\n    , emp_cgc AS CNPJ\n    , emp_nome_fantasia AS DS_UNIDADE\n    , emp_nome_fantasia AS MARCA\n    , 0 AS CD_PROCEDENCIA\n    , 'NAO ENCONTRADO' AS DS_PROCEDENCIA\n    , 'NAO ENCONTRADO' AS ID\n    , CONVERT(INT, DAY(osm_dthr)) AS DIA\n    , CONVERT(INT, MONTH(osm_dthr)) AS MES\n    , CONVERT(INT, YEAR(osm_dthr)) AS ANO,\n'Smart INOB' as BASE\nFROM osm\nINNER JOIN smm\n    ON smm_osm_serie = osm_serie\n        AND smm_osm = osm_num\nINNER JOIN pac\n    ON pac_reg = osm_pac\nINNER JOIN cnv\n    ON osm_cnv = cnv_cod\nINNER JOIN str\n    ON str_cod = osm_str\nINNER JOIN psv\n    ON psv_cod = osm_mreq\nLEFT OUTER JOIN str str_e\n    ON str.str_str_cod = str_e.str_cod\nLEFT OUTER JOIN emp\n    ON str_e.str_emp_cod = emp_cod\nWHERE 1 = 1\n    AND (\n        smm_pacote IS NULL\n        OR (smm_pacote = 'C')\n        )\n    AND smm_sfat NOT IN ('C')\n\nAND osm_dthr BETWEEN GETDATE() - 730 AND GETDATE()",
								"queryTimeout": "02:00:00",
								"partitionOption": "None"
							},
							"sink": {
								"type": "AzureSqlSink"
							},
							"enableStaging": false
						},
						"inputs": [
							{
								"referenceName": "SMART_HOSL_PrdDataSet",
								"type": "DatasetReference",
								"parameters": {}
							}
						],
						"outputs": [
							{
								"referenceName": "AZ_SQL_TB_Atendimento",
								"type": "DatasetReference",
								"parameters": {}
							}
						]
					},
					{
						"name": "Agendamentos INOB",
						"type": "Copy",
						"dependsOn": [
							{
								"activity": "Wait1",
								"dependencyConditions": [
									"Succeeded"
								]
							}
						],
						"policy": {
							"timeout": "7.00:00:00",
							"retry": 0,
							"retryIntervalInSeconds": 30,
							"secureOutput": false,
							"secureInput": false
						},
						"userProperties": [],
						"typeProperties": {
							"source": {
								"type": "SqlServerSource",
								"sqlReaderQuery": "SELECT DISTINCT AGM_PAC AS CD_PESSOA_FISICA\n    , agm.agm_cnv_cod AS CD_CONVENIO\n    , emp_cgc AS CNPJ\n    , CONVERT(DATE, AGM_HINI) AS DATA_AGENDA\n    , LEFT(CONVERT(VARCHAR(12), agm_hini, 114), 8) AS HORA_AGENDA\n    , CASE AGM_ATEND\n        WHEN 'CRG'\n            THEN 'Cirurgia'\n        WHEN 'ASS'\n            THEN 'Consulta'\n        when '' then 'Consulta'\n        ELSE 'Outros'\n        END AS TIPO_AGENDA\n    , pac.PAC_NOME AS NM_PACIENTE\n    , smk.smk_nome AS DS_PROCEDIMENTO_PRINC\n    , ' ' DS_PROCEDIMENTO_ADIC\n    , 1 AS IE_QUANTIDADE\n    , USR_NOME AS NM_USUARIO\n    , psv_nome AS NM_MEDICO\n    , EMP_NOME_FANTASIA AS DS_UNIDADE\n    , EMP_NOME_FANTASIA AS MARCA\n    , CASE \n        WHEN AGM_STAT = 'A'\n            THEN 'Aberta'\n        WHEN AGM_STAT = 'E'\n            THEN 'Executada'\n        WHEN AGM_STAT = 'C'\n            THEN 'Cancelada'\n        WHEN AGM_STAT = 'B'\n            THEN 'Bloqueada'\n        END STATUS_AGENDA\n    , CONVERT(VARCHAR, convert(VARCHAR, AGM_OSM_SERIE) + convert(VARCHAR, AGM_OSM_NUM)) AS NR_ATENDIMENTO\n    , AGM_num AS NR_SEQUENCIA\n    , '' ID\n    , '' AS CD_PROCEDENCIA\n    , agm_proc AS DS_PROCEDENCIA\n    , agm.AGM_DTMRC AS DT_AGENDAMENTO\n    , CONVERT(INT, DAY(AGM_HINI)) AS DIA\n    , CONVERT(INT, MONTH(AGM_HINI)) AS MES\n    , CONVERT(INT, YEAR(AGM_HINI)) AS ANO\n    , ' ' DS_CLASSIFICACAO\n    , ' ' DS_AGRUPAMENTO\n    , agm.AGM_CANC_MOT_COD AS CD_MOTIVO_CANCELAMENTO\n    , agm.AGM_CANC_MOT_TIPO AS DS_MOTIVO_CANCELAMENTO\n    , agm_med AS CD_AGENDA,\n'Smart INOB' as BASE\nFROM agm\nINNER JOIN usr\n    ON (agm.agm_usr_login = usr.usr_login)\nINNER JOIN psv\n    ON (psv.psv_cod = agm.agm_med)\nINNER JOIN smk\n    ON (\n            agm_smk = smk_cod\n            AND agm_tpsmk = smk_tipo\n            )\nINNER JOIN pac\n    ON (pac_reg = agm_pac)\nINNER JOIN loc\n    ON (AGM_LOC = LOC_COD)\nINNER JOIN str\n    ON (LOC_STR = STR.STR_COD)\nINNER JOIN str str_e\n    ON (STR.STR_STR_COD = STR_E.STR_COD)\nINNER JOIN cnv\n    ON (CNV_COD = AGM_CNV_COD)\nLEFT OUTER JOIN ctf ct1\n    ON (\n            ct1.ctf_cod = smk_ctf\n            AND ct1.ctf_tipo = smk_tipo\n            )\nLEFT OUTER JOIN emp\n    ON emp_cod = str_e.str_emp_cod\n\nWHERE AGM_DTMRC BETWEEN GETDATE() - 730 AND GETDATE()",
								"queryTimeout": "02:00:00",
								"partitionOption": "None"
							},
							"sink": {
								"type": "AzureSqlSink"
							},
							"enableStaging": false
						},
						"inputs": [
							{
								"referenceName": "SMART_HOSL_PrdDataSet",
								"type": "DatasetReference",
								"parameters": {}
							}
						],
						"outputs": [
							{
								"referenceName": "AZ_SQL_TB_Agendamento",
								"type": "DatasetReference",
								"parameters": {}
							}
						]
					},
					{
						"name": "Usuarios INOB",
						"type": "Copy",
						"dependsOn": [
							{
								"activity": "Wait1",
								"dependencyConditions": [
									"Succeeded"
								]
							}
						],
						"policy": {
							"timeout": "7.00:00:00",
							"retry": 0,
							"retryIntervalInSeconds": 30,
							"secureOutput": false,
							"secureInput": false
						},
						"userProperties": [],
						"typeProperties": {
							"source": {
								"type": "SqlServerSource",
								"sqlReaderQuery": "select \nusr_login as NM_USUARIO,\nusr_nome as DS_USUARIO,\nusr_status as IE_SITUACAO,\nusr_dt_alter_senha as DT_ATUALIZACAO,\n'INOB' AS DS_UNIDADE,\n'00363702000130' as CNPJ,\n'INOB' as MARCA,\n'Smart INOB' as BASE\nfrom usr",
								"queryTimeout": "02:00:00",
								"partitionOption": "None"
							},
							"sink": {
								"type": "AzureSqlSink"
							},
							"enableStaging": false
						},
						"inputs": [
							{
								"referenceName": "SMART_HOSL_PrdDataSet",
								"type": "DatasetReference",
								"parameters": {}
							}
						],
						"outputs": [
							{
								"referenceName": "AZ_SQL_TB_Usuario",
								"type": "DatasetReference",
								"parameters": {}
							}
						]
					},
					{
						"name": "Consulta INOB",
						"type": "Copy",
						"dependsOn": [
							{
								"activity": "Wait1",
								"dependencyConditions": [
									"Succeeded"
								]
							}
						],
						"policy": {
							"timeout": "7.00:00:00",
							"retry": 0,
							"retryIntervalInSeconds": 30,
							"secureOutput": false,
							"secureInput": false
						},
						"userProperties": [],
						"typeProperties": {
							"source": {
								"type": "SqlServerSource",
								"sqlReaderQuery": "SELECT \nRCL_SMM AS NR_SEQUENCIA,\nCONVERT(DATE,RCL_DTHR_ATUAL) AS DT_ATUALIZACAO,\nCONVERT(VARCHAR,RCL_DTHR_ATUAL,108) as HR_ATUALIZACAO,\n\nCONVERT(VARCHAR,CONVERT(VARCHAR,RCL_OSM_SERIE) + CONVERT(VARCHAR,RCL_OSM)) AS NR_ATENDIMENTO, \n\nRCL_MED AS CD_MEDICO,\nPSV_APEL AS NM_MEDICO,\n'' AS DS_RETORNO,\nCONVERT(VARCHAR,RCL_LAUDO_RTF) AS DS_CONDUTA,\nRCL_PAC AS CD_PESSOA_FISICA,\nCONVERT(VARCHAR,RCL_TXT) AS DS_DIAGNOSTICO,\n'INOB' AS DS_UNIDADE,\n'00363702000130' as CNPJ,\n'INOB' AS MARCA,\n'Smart INOB' as BASE\nFROM RCL\nINNER JOIN PSV ON PSV_COD = RCL_MED\n\nWHERE RCL_DTHR_ATUAL BETWEEN GETDATE() - 730 AND GETDATE()",
								"queryTimeout": "02:00:00",
								"partitionOption": "None"
							},
							"sink": {
								"type": "AzureSqlSink"
							},
							"enableStaging": false
						},
						"inputs": [
							{
								"referenceName": "SMART_HOSL_PrdDataSet",
								"type": "DatasetReference",
								"parameters": {}
							}
						],
						"outputs": [
							{
								"referenceName": "AZ_SQL_TB_Consulta",
								"type": "DatasetReference",
								"parameters": {}
							}
						]
					},
					{
						"name": "Agendas INOB",
						"type": "Copy",
						"dependsOn": [
							{
								"activity": "Wait1",
								"dependencyConditions": [
									"Succeeded"
								]
							}
						],
						"policy": {
							"timeout": "7.00:00:00",
							"retry": 0,
							"retryIntervalInSeconds": 30,
							"secureOutput": false,
							"secureInput": false
						},
						"userProperties": [],
						"typeProperties": {
							"source": {
								"type": "SqlServerSource",
								"sqlReaderQuery": "SELECT distinct agd_med AS CD_AGENDA \n    , 0 AS DS_AGENDA\n    , 0 CD_TIPO_AGENDA\n    , psv_cod AS CD_PESSOA_FISICA\n    , emp_cgc AS CNPJ\n    , '' AS DS_AREA_ATUACAO\n    , 'A' AS IE_SITUACAO,\n'Smart INOB' as BASE\n    -- , CASE \n    --     WHEN (agd_dt_reconstr IS not NULL and AGD_DT_GERA is not null)\n    --         THEN agd_dt_reconstr\n    --     WHEN (agd_dt_reconstr IS NULL and AGD_DT_GERA is not null)\n    --         THEN agd_dt_gera\n    --     ELSE AGD_DT_GERA\n    --     END AS DT_ATUALIZACAO\nFROM agd\nINNER JOIN PSV\n    ON agd_med = psv_cod\nINNER JOIN loc\n    ON loc_cod = agd_loc\nINNER JOIN str\n    ON str_cod = loc_str\nLEFT OUTER JOIN str str_e\n    ON str_e.str_cod = str.str_str_cod\nLEFT OUTER JOIN emp\n    ON emp_cod = str_e.str_emp_cod",
								"queryTimeout": "02:00:00",
								"partitionOption": "None"
							},
							"sink": {
								"type": "AzureSqlSink"
							},
							"enableStaging": false
						},
						"inputs": [
							{
								"referenceName": "SMART_HOSL_PrdDataSet",
								"type": "DatasetReference",
								"parameters": {}
							}
						],
						"outputs": [
							{
								"referenceName": "AZ_SQL_TB_Agenda",
								"type": "DatasetReference",
								"parameters": {}
							}
						]
					},
					{
						"name": "Execute Pipeline IOF",
						"type": "ExecutePipeline",
						"dependsOn": [
							{
								"activity": "Atendimento INOB",
								"dependencyConditions": [
									"Succeeded"
								]
							},
							{
								"activity": "Agendamentos INOB",
								"dependencyConditions": [
									"Succeeded"
								]
							},
							{
								"activity": "Usuarios INOB",
								"dependencyConditions": [
									"Succeeded"
								]
							},
							{
								"activity": "Consulta INOB",
								"dependencyConditions": [
									"Succeeded"
								]
							},
							{
								"activity": "Agendas INOB",
								"dependencyConditions": [
									"Succeeded"
								]
							}
						],
						"userProperties": [],
						"typeProperties": {
							"pipeline": {
								"referenceName": "Geral Atendimentos IOF",
								"type": "PipelineReference"
							},
							"waitOnCompletion": true,
							"parameters": {}
						}
					}
				],
				"folder": {
					"name": "Atendimento"
				},
				"annotations": []
			},
			"dependsOn": []
		},
		{
			"name": "[concat(parameters('factoryName'), '/Producao Medica Itabuna')]",
			"type": "Microsoft.DataFactory/factories/pipelines",
			"apiVersion": "2018-06-01",
			"properties": {
				"description": "Pipeline desenvolvido para extração de informações de produção medica das unidades com o sistema Tasy e Smart.",
				"activities": [
					{
						"name": "Wait1",
						"type": "Wait",
						"dependsOn": [],
						"userProperties": [],
						"typeProperties": {
							"waitTimeInSeconds": 1
						}
					},
					{
						"name": "Producao Procedimentos Itabuna",
						"type": "Copy",
						"dependsOn": [
							{
								"activity": "Wait1",
								"dependencyConditions": [
									"Succeeded"
								]
							}
						],
						"policy": {
							"timeout": "7.00:00:00",
							"retry": 0,
							"retryIntervalInSeconds": 30,
							"secureOutput": false,
							"secureInput": false
						},
						"userProperties": [],
						"typeProperties": {
							"source": {
								"type": "SqlServerSource",
								"sqlReaderQuery": "select\n        'Smart Itabuna' as BASE\n        ,EMP_CGC as CNPJ\n        ,gcc_descr as MARCA\n        ,smm_dthr_alter as DT_ATUALIZACAO \n        ,convert(varchar,osm_serie) + convert(varchar,osm_num) as NR_ATENDIMENTO --duvida\n        ,osm_dthr as DT_ENTRADA\n        ,convert(varchar,osm_serie) + convert(varchar,osm_num) as NR_INTERNO_CONTA --duvida\n        ,osm_pac as CD_PESSOA_FISICA\n        ,pac_nasc as DT_NASCIMENTO\n        ,pac_numcpf as NR_CPF\n        ,pac_sexo as IE_SEXO\n        ,pac_cep as NR_CEP\n        ,case when isnumeric(pac_cid) = 1 then (select cde_nome from cde where cde_cod = pac_cid)\n        else pac_cid end as DS_CIDADE\n        ,pac_nome as DS_PESSOA_FISICA\n        ,cnv_cod as CD_CONVENIO\n        ,cnv_nome as DS_CONVENIO\n        ,psv_exe.psv_cod as CD_MEDICO_EXECUTOR\n        ,psv_exe.psv_apel as DS_MEDICO_EXECUTOR\n        ,psv_req.psv_cod as CD_MEDICO_REQUISITANTE\n        ,psv_req.psv_apel as DS_MEDICO_REQUISITANTE\n        ,isnull(tab_padrao,0) as IE_ORIGEM_PROCEDIMENTO\n        ,smm_cod as CD_PROCEDIMENTO\n        ,smk_rot as DS_PROCEDIMENTO\n        ,case ctf_categ \n            when 'C' then 'Consulta'\n            when 'E' then 'Exames'\n            when 'R' then 'Cirurgia'\n            when 'T' then 'Taxas'\n            when 'A' then 'Terapia'\n            when 'O' then 'Outras'\n            when 'M' then 'Materiais'\n            when 'S' then 'Materiais Especiais'\n            when 'N' then 'Medicamentos'\n            when 'G' then 'Gases'\n            when 'O' then 'Outros'\n        end as DS_CLASSIFICACAO\n        ,smm_qt as QT_PROCEDIMENTO\n        ,smm_vlr + isnull(smm_ajuste_vlr,0) as VL_PROCEDIMENTO\n        ,case \n            when smm_fat_serie is not null then 2\n        else 1 end AS IE_STATUS_ACERTO\n        ,case \n            when smm_fat_serie is not null then 'Definitivo'\n        else 'Provisório' end as STATUS_CONTA\n        ,0 as CD_TUSS,\n        0 as NR_SEQ_PROC_INTERNO\n    from \n        osm\n        inner join smm on (smm_osm_serie = osm_serie and smm_osm = osm_num)\n        inner join str str_osm on (str_osm.str_cod = osm_str)\n        inner join str str_emp on (str_osm.str_str_cod = str_emp.str_cod)\n        inner join pac on (pac_reg = osm_pac)inner join cnv on (cnv_cod = osm_cnv)\n        inner join psv psv_exe on (psv_exe.psv_cod = smm_med)\n        inner join psv psv_req on (psv_req.psv_cod = smm_med)\n        inner join smk on (smk_cod = smm_cod and smk_tipo = smm_tpcod)\n        inner join gcc on (str_emp.str_cod = gcc_cod)\n        \n        inner join emp ON (emp_cod = str_emp.str_emp_cod)\n\n        inner join ctf on (ctf_cod = smk_ctf and ctf_tipo = smk_tipo)\n        left outer join tab on (tab_cod = smm_tab_cod)\n    where \n        1 = 1\n        and convert(varchar(10), osm_dthr, 103) = convert(varchar(10), getdate(), 103)\nand osm_dthr between GETDATE() - 730 and GETDATE()",
								"queryTimeout": "02:00:00",
								"partitionOption": "None"
							},
							"sink": {
								"type": "AzureSqlSink"
							},
							"enableStaging": false
						},
						"inputs": [
							{
								"referenceName": "SMART_ITABUNA_PrdDataSet",
								"type": "DatasetReference",
								"parameters": {}
							}
						],
						"outputs": [
							{
								"referenceName": "AZ_SQL_TB_Unidade_Producao_Medica",
								"type": "DatasetReference",
								"parameters": {}
							}
						]
					},
					{
						"name": "Convenios",
						"type": "Copy",
						"dependsOn": [
							{
								"activity": "Wait1",
								"dependencyConditions": [
									"Succeeded"
								]
							}
						],
						"policy": {
							"timeout": "7.00:00:00",
							"retry": 0,
							"retryIntervalInSeconds": 30,
							"secureOutput": false,
							"secureInput": false
						},
						"userProperties": [],
						"typeProperties": {
							"source": {
								"type": "SqlServerSource",
								"sqlReaderQuery": "select cnv_cod AS CD_CONVENIO, cnv.cnv_nome AS DS_CONVENIO, gcc.gcc_cod AS CD_ESTABELECIMENTO, emp.emp_cgc AS CNPJ\nfrom cnv,\n     gcc,\n     str,\n     emp\nwhere gcc.gcc_str_cod = str_cod\nand str_emp_cod = emp_cod\nand emp_cgc <> '-'\nand cnv_cod <> '999'\nand cnv_stat = 'A'",
								"queryTimeout": "02:00:00",
								"partitionOption": "None"
							},
							"sink": {
								"type": "AzureSqlSink"
							},
							"enableStaging": false
						},
						"inputs": [
							{
								"referenceName": "SMART_ITABUNA_PrdDataSet",
								"type": "DatasetReference",
								"parameters": {}
							}
						],
						"outputs": [
							{
								"referenceName": "AZ_SQL_TB_Convenio",
								"type": "DatasetReference",
								"parameters": {}
							}
						]
					},
					{
						"name": "Setor",
						"type": "Copy",
						"dependsOn": [
							{
								"activity": "Wait1",
								"dependencyConditions": [
									"Succeeded"
								]
							}
						],
						"policy": {
							"timeout": "7.00:00:00",
							"retry": 0,
							"retryIntervalInSeconds": 30,
							"secureOutput": false,
							"secureInput": false
						},
						"userProperties": [],
						"typeProperties": {
							"source": {
								"type": "SqlServerSource",
								"sqlReaderQuery": "SELECT STR_COD AS CD_SETOR_ATENDIMENTO, \nSTR_NOME AS DS_SETOR_ATENDIMENTO, \nEMP_CGC AS CNPJ\nFROM STR, EMP\nWHERE STR_EMP_COD = EMP_COD\nAND EMP_CGC <> '-'\nAND STR_COD <> '999'",
								"queryTimeout": "02:00:00",
								"partitionOption": "None"
							},
							"sink": {
								"type": "AzureSqlSink"
							},
							"enableStaging": false
						},
						"inputs": [
							{
								"referenceName": "SMART_ITABUNA_PrdDataSet",
								"type": "DatasetReference",
								"parameters": {}
							}
						],
						"outputs": [
							{
								"referenceName": "AZ_SQL_TB_Setor",
								"type": "DatasetReference",
								"parameters": {}
							}
						]
					},
					{
						"name": "Execute Itaigara",
						"type": "ExecutePipeline",
						"dependsOn": [
							{
								"activity": "Producao Procedimentos Itabuna",
								"dependencyConditions": [
									"Succeeded"
								]
							},
							{
								"activity": "Convenios",
								"dependencyConditions": [
									"Succeeded"
								]
							},
							{
								"activity": "Setor",
								"dependencyConditions": [
									"Succeeded"
								]
							}
						],
						"userProperties": [],
						"typeProperties": {
							"pipeline": {
								"referenceName": "Producao Medica Itaigara",
								"type": "PipelineReference"
							},
							"waitOnCompletion": true,
							"parameters": {}
						}
					}
				],
				"folder": {
					"name": "Produção Médica CSI"
				},
				"annotations": []
			},
			"dependsOn": [
				"[concat(variables('factoryId'), '/pipelines/Producao Medica Itaigara')]"
			]
		},
		{
			"name": "[concat(parameters('factoryName'), '/Geral Atendimentos HOSL')]",
			"type": "Microsoft.DataFactory/factories/pipelines",
			"apiVersion": "2018-06-01",
			"properties": {
				"description": "Alimenta as informações das tabelas:\n\nAtendimento_ Unidade \nAgendamento_Unidade\nUsuarios_Unidade\nConsultas_Unidade\nAgendas Unidade\n\nPara extração de relatórios do call center.",
				"activities": [
					{
						"name": "Wait1",
						"type": "Wait",
						"dependsOn": [],
						"userProperties": [],
						"typeProperties": {
							"waitTimeInSeconds": 1
						}
					},
					{
						"name": "Atendimento HOSL",
						"type": "Copy",
						"dependsOn": [
							{
								"activity": "Wait1",
								"dependencyConditions": [
									"Succeeded"
								]
							}
						],
						"policy": {
							"timeout": "7.00:00:00",
							"retry": 0,
							"retryIntervalInSeconds": 30,
							"secureOutput": false,
							"secureInput": false
						},
						"userProperties": [],
						"typeProperties": {
							"source": {
								"type": "SqlServerSource",
								"sqlReaderQuery": "SELECT DISTINCT pac_reg AS CD_PESSOA_FISICA\n    , rtrim(ltrim(pac_nome)) AS NM_PESSOA_FISICA\n    , convert(CHAR(10), osm_dthr, 121) AS DT_ENTRADA\n    , LEFT(CONVERT(VARCHAR(12), osm_dthr, 114),8) AS HR_ENTRADA\n    , smm_med AS NM_MEDICO\n    , osm_cnv AS CD_CONVENIO\n    , cnv_nome AS DS_CONVENIO\n    , convert(VARCHAR, (convert(VARCHAR, osm_serie) + convert(VARCHAR, osm_num))) AS NR_ATENDIMENTO\n    , emp_cgc AS CNPJ\n    , emp_nome_fantasia AS DS_UNIDADE\n    , emp_nome_fantasia AS MARCA\n    , 0 AS CD_PROCEDENCIA\n    , 'NAO ENCONTRADO' AS DS_PROCEDENCIA\n    , 'NAO ENCONTRADO' AS ID\n    , CONVERT(INT, DAY(osm_dthr)) AS DIA\n    , CONVERT(INT, MONTH(osm_dthr)) AS MES\n    , CONVERT(INT, YEAR(osm_dthr)) AS ANO,\n'Smart HOSL' as BASE\nFROM osm\nINNER JOIN smm\n    ON smm_osm_serie = osm_serie\n        AND smm_osm = osm_num\nINNER JOIN pac\n    ON pac_reg = osm_pac\nINNER JOIN cnv\n    ON osm_cnv = cnv_cod\nINNER JOIN str\n    ON str_cod = osm_str\nINNER JOIN psv\n    ON psv_cod = osm_mreq\nLEFT OUTER JOIN str str_e\n    ON str.str_str_cod = str_e.str_cod\nLEFT OUTER JOIN emp\n    ON str_e.str_emp_cod = emp_cod\nWHERE 1 = 1\n    AND (\n        smm_pacote IS NULL\n        OR (smm_pacote = 'C')\n        )\n    AND smm_sfat NOT IN ('C')\n\nAND osm_dthr BETWEEN GETDATE() - 730 AND GETDATE()",
								"queryTimeout": "02:00:00",
								"partitionOption": "None"
							},
							"sink": {
								"type": "AzureSqlSink"
							},
							"enableStaging": false,
							"enableSkipIncompatibleRow": true
						},
						"inputs": [
							{
								"referenceName": "SMART_HOSL_PrdDataSet",
								"type": "DatasetReference",
								"parameters": {}
							}
						],
						"outputs": [
							{
								"referenceName": "AZ_SQL_TB_Atendimento",
								"type": "DatasetReference",
								"parameters": {}
							}
						]
					},
					{
						"name": "Agendamentos HOSL",
						"type": "Copy",
						"dependsOn": [
							{
								"activity": "Wait1",
								"dependencyConditions": [
									"Succeeded"
								]
							}
						],
						"policy": {
							"timeout": "7.00:00:00",
							"retry": 0,
							"retryIntervalInSeconds": 30,
							"secureOutput": false,
							"secureInput": false
						},
						"userProperties": [],
						"typeProperties": {
							"source": {
								"type": "SqlServerSource",
								"sqlReaderQuery": "SELECT DISTINCT AGM_PAC AS CD_PESSOA_FISICA\n    , agm.agm_cnv_cod AS CD_CONVENIO\n    , emp_cgc AS CNPJ\n    , CONVERT(DATE, AGM_HINI) AS DATA_AGENDA\n    , LEFT(CONVERT(VARCHAR(12), agm_hini, 114), 8) AS HORA_AGENDA\n    , CASE AGM_ATEND\n        WHEN 'CRG'\n            THEN 'Cirurgia'\n        WHEN 'ASS'\n            THEN 'Consulta'\n        when '' then 'Consulta'\n        ELSE 'Outros'\n        END AS TIPO_AGENDA\n    , pac.PAC_NOME AS NM_PACIENTE\n    , smk.smk_nome AS DS_PROCEDIMENTO_PRINC\n    , ' ' DS_PROCEDIMENTO_ADIC\n    , 1 AS IE_QUANTIDADE\n    , USR_NOME AS NM_USUARIO\n    , psv_nome AS NM_MEDICO\n    , EMP_NOME_FANTASIA AS DS_UNIDADE\n    , EMP_NOME_FANTASIA AS MARCA\n    , CASE \n        WHEN AGM_STAT = 'A'\n            THEN 'Aberta'\n        WHEN AGM_STAT = 'E'\n            THEN 'Executada'\n        WHEN AGM_STAT = 'C'\n            THEN 'Cancelada'\n        WHEN AGM_STAT = 'B'\n            THEN 'Bloqueada'\n        END STATUS_AGENDA\n    , CONVERT(VARCHAR, convert(VARCHAR, AGM_OSM_SERIE) + convert(VARCHAR, AGM_OSM_NUM)) AS NR_ATENDIMENTO\n    , AGM_num AS NR_SEQUENCIA\n    , '' ID\n    , '' AS CD_PROCEDENCIA\n    , agm_proc AS DS_PROCEDENCIA\n    , agm.AGM_DTMRC AS DT_AGENDAMENTO\n    , CONVERT(INT, DAY(AGM_HINI)) AS DIA\n    , CONVERT(INT, MONTH(AGM_HINI)) AS MES\n    , CONVERT(INT, YEAR(AGM_HINI)) AS ANO\n    , ' ' DS_CLASSIFICACAO\n    , ' ' DS_AGRUPAMENTO\n    , agm.AGM_CANC_MOT_COD AS CD_MOTIVO_CANCELAMENTO\n    , agm.AGM_CANC_MOT_TIPO AS DS_MOTIVO_CANCELAMENTO\n    , agm_med AS CD_AGENDA,\n    'Smart HOSL' as BASE\nFROM agm\nINNER JOIN usr\n    ON (agm.agm_usr_login = usr.usr_login)\nINNER JOIN psv\n    ON (psv.psv_cod = agm.agm_med)\nINNER JOIN smk\n    ON (\n            agm_smk = smk_cod\n            AND agm_tpsmk = smk_tipo\n            )\nINNER JOIN pac\n    ON (pac_reg = agm_pac)\nINNER JOIN loc\n    ON (AGM_LOC = LOC_COD)\nINNER JOIN str\n    ON (LOC_STR = STR.STR_COD)\nINNER JOIN str str_e\n    ON (STR.STR_STR_COD = STR_E.STR_COD)\nINNER JOIN cnv\n    ON (CNV_COD = AGM_CNV_COD)\nLEFT OUTER JOIN ctf ct1\n    ON (\n            ct1.ctf_cod = smk_ctf\n            AND ct1.ctf_tipo = smk_tipo\n            )\nLEFT OUTER JOIN emp\n    ON emp_cod = str_e.str_emp_cod\n\nWHERE AGM_DTMRC BETWEEN GETDATE() - 730 AND GETDATE()",
								"queryTimeout": "02:00:00",
								"partitionOption": "None"
							},
							"sink": {
								"type": "AzureSqlSink"
							},
							"enableStaging": false,
							"enableSkipIncompatibleRow": true
						},
						"inputs": [
							{
								"referenceName": "SMART_HOSL_PrdDataSet",
								"type": "DatasetReference",
								"parameters": {}
							}
						],
						"outputs": [
							{
								"referenceName": "AZ_SQL_TB_Agendamento",
								"type": "DatasetReference",
								"parameters": {}
							}
						]
					},
					{
						"name": "Usuarios HOSL",
						"type": "Copy",
						"dependsOn": [
							{
								"activity": "Wait1",
								"dependencyConditions": [
									"Succeeded"
								]
							}
						],
						"policy": {
							"timeout": "7.00:00:00",
							"retry": 0,
							"retryIntervalInSeconds": 30,
							"secureOutput": false,
							"secureInput": false
						},
						"userProperties": [],
						"typeProperties": {
							"source": {
								"type": "SqlServerSource",
								"sqlReaderQuery": "select\nusr_login as NM_USUARIO,\nusr_nome as DS_USUARIO,\nusr_status as IE_SITUACAO,\nusr_dt_alter_senha as DT_ATUALIZACAO,\n'HOSPITAL DE OLHOS SANTA LUZIA SS LTDA' AS DS_UNIDADE,\n'12305371000160' as CNPJ,\n'HOSL' as MARCA,\n'Smart HOSL' as BASE\nfrom usr",
								"queryTimeout": "02:00:00",
								"partitionOption": "None"
							},
							"sink": {
								"type": "AzureSqlSink"
							},
							"enableStaging": false
						},
						"inputs": [
							{
								"referenceName": "SMART_HOSL_PrdDataSet",
								"type": "DatasetReference",
								"parameters": {}
							}
						],
						"outputs": [
							{
								"referenceName": "AZ_SQL_TB_Usuario",
								"type": "DatasetReference",
								"parameters": {}
							}
						]
					},
					{
						"name": "Consulta HOSL",
						"type": "Copy",
						"dependsOn": [
							{
								"activity": "Wait1",
								"dependencyConditions": [
									"Succeeded"
								]
							}
						],
						"policy": {
							"timeout": "7.00:00:00",
							"retry": 0,
							"retryIntervalInSeconds": 30,
							"secureOutput": false,
							"secureInput": false
						},
						"userProperties": [],
						"typeProperties": {
							"source": {
								"type": "SqlServerSource",
								"sqlReaderQuery": "SELECT\nRCL_SMM AS NR_SEQUENCIA,\nCONVERT(DATE,RCL_DTHR_ATUAL) AS DT_ATUALIZACAO,\nCONVERT(VARCHAR,RCL_DTHR_ATUAL,108) as HR_ATUALIZACAO,\n\nCONVERT(VARCHAR,CONVERT(VARCHAR,RCL_OSM_SERIE) + CONVERT(VARCHAR,RCL_OSM)) AS NR_ATENDIMENTO, \n\nRCL_MED AS CD_MEDICO,\nPSV_APEL AS NM_MEDICO,\n'' AS DS_RETORNO,\nCONVERT(VARCHAR,RCL_LAUDO_RTF) AS DS_CONDUTA,\nRCL_PAC AS CD_PESSOA_FISICA,\nCONVERT(VARCHAR,RCL_TXT) AS DS_DIAGNOSTICO,\n'HOSPITAL DE OLHOS SANTA LUZIA SS LTDA' AS DS_UNIDADE,\n'12305371000160' as CNPJ,\n'HOSL' AS MARCA,\n'Smart HOSL' as BASE\nFROM RCL\nINNER JOIN PSV ON PSV_COD = RCL_MED\n\nWHERE RCL_DTHR_ATUAL BETWEEN GETDATE() - 730 AND GETDATE()",
								"queryTimeout": "02:00:00",
								"partitionOption": "None"
							},
							"sink": {
								"type": "AzureSqlSink"
							},
							"enableStaging": false,
							"enableSkipIncompatibleRow": true
						},
						"inputs": [
							{
								"referenceName": "SMART_HOSL_PrdDataSet",
								"type": "DatasetReference",
								"parameters": {}
							}
						],
						"outputs": [
							{
								"referenceName": "AZ_SQL_TB_Consulta",
								"type": "DatasetReference",
								"parameters": {}
							}
						]
					},
					{
						"name": "Agendas HOSL",
						"type": "Copy",
						"dependsOn": [
							{
								"activity": "Wait1",
								"dependencyConditions": [
									"Succeeded"
								]
							}
						],
						"policy": {
							"timeout": "7.00:00:00",
							"retry": 0,
							"retryIntervalInSeconds": 30,
							"secureOutput": false,
							"secureInput": false
						},
						"userProperties": [],
						"typeProperties": {
							"source": {
								"type": "SqlServerSource",
								"sqlReaderQuery": "SELECT distinct agd_med AS CD_AGENDA \n    , 0 AS DS_AGENDA\n    , 0 CD_TIPO_AGENDA\n    , psv_cod AS CD_PESSOA_FISICA\n    , emp_cgc AS CNPJ\n    , '' AS DS_AREA_ATUACAO\n    , 'A' AS IE_SITUACAO,\n    -- , CASE \n    --     WHEN (agd_dt_reconstr IS not NULL and AGD_DT_GERA is not null)\n    --         THEN agd_dt_reconstr\n    --     WHEN (agd_dt_reconstr IS NULL and AGD_DT_GERA is not null)\n    --         THEN agd_dt_gera\n    --     ELSE AGD_DT_GERA\n    --     END AS DT_ATUALIZACAO,\n'Smart HOSL' as BASE\nFROM agd\nINNER JOIN PSV\n    ON agd_med = psv_cod\nINNER JOIN loc\n    ON loc_cod = agd_loc\nINNER JOIN str\n    ON str_cod = loc_str\nLEFT OUTER JOIN str str_e\n    ON str_e.str_cod = str.str_str_cod\nLEFT OUTER JOIN emp\n    ON emp_cod = str_e.str_emp_cod",
								"queryTimeout": "02:00:00",
								"partitionOption": "None"
							},
							"sink": {
								"type": "AzureSqlSink"
							},
							"enableStaging": false
						},
						"inputs": [
							{
								"referenceName": "SMART_HOSL_PrdDataSet",
								"type": "DatasetReference",
								"parameters": {}
							}
						],
						"outputs": [
							{
								"referenceName": "AZ_SQL_TB_Agenda",
								"type": "DatasetReference",
								"parameters": {}
							}
						]
					},
					{
						"name": "Execute Pipeline INOB",
						"type": "ExecutePipeline",
						"dependsOn": [
							{
								"activity": "Atendimento HOSL",
								"dependencyConditions": [
									"Succeeded"
								]
							},
							{
								"activity": "Agendamentos HOSL",
								"dependencyConditions": [
									"Succeeded"
								]
							},
							{
								"activity": "Usuarios HOSL",
								"dependencyConditions": [
									"Succeeded"
								]
							},
							{
								"activity": "Consulta HOSL",
								"dependencyConditions": [
									"Succeeded"
								]
							},
							{
								"activity": "Agendas HOSL",
								"dependencyConditions": [
									"Succeeded"
								]
							}
						],
						"userProperties": [],
						"typeProperties": {
							"pipeline": {
								"referenceName": "Geral Atendimentos INOB - Smart",
								"type": "PipelineReference"
							},
							"waitOnCompletion": true,
							"parameters": {}
						}
					}
				],
				"folder": {
					"name": "Atendimento"
				},
				"annotations": []
			},
			"dependsOn": [
				"[concat(variables('factoryId'), '/pipelines/Geral Atendimentos INOB - Smart')]"
			]
		},
		{
			"name": "[concat(parameters('factoryName'), '/Producao Medica IOF')]",
			"type": "Microsoft.DataFactory/factories/pipelines",
			"apiVersion": "2018-06-01",
			"properties": {
				"description": "Pipeline desenvolvido para extração de informações de produção medica das unidades com o sistema Tasy e Smart.",
				"activities": [
					{
						"name": "Wait1",
						"type": "Wait",
						"dependsOn": [],
						"userProperties": [],
						"typeProperties": {
							"waitTimeInSeconds": 1
						}
					},
					{
						"name": "Producao Procedimentos IOF",
						"type": "Copy",
						"dependsOn": [
							{
								"activity": "Wait1",
								"dependencyConditions": [
									"Succeeded"
								]
							}
						],
						"policy": {
							"timeout": "7.00:00:00",
							"retry": 0,
							"retryIntervalInSeconds": 30,
							"secureOutput": false,
							"secureInput": false
						},
						"userProperties": [],
						"typeProperties": {
							"source": {
								"type": "SqlServerSource",
								"sqlReaderQuery": "select \n        'Smart IOF' as BASE\n        ,EMP_CGC as CNPJ\n        ,gcc.gcc_descr as MARCA\n        ,smm_dthr_alter as DT_ATUALIZACAO \n        ,convert(varchar,osm_serie) + convert(varchar,osm_num) as NR_ATENDIMENTO --duvida\n        ,osm_dthr as DT_ENTRADA\n        ,convert(varchar,osm_serie) + convert(varchar,osm_num) as NR_INTERNO_CONTA --duvida\n        ,osm_pac as CD_PESSOA_FISICA\n        ,pac_nasc as DT_NASCIMENTO\n        ,pac_numcpf as NR_CPF\n        ,pac_sexo as IE_SEXO\n        ,pac_cep as NR_CEP\n        ,case \n            when isnumeric(pac_cid) = 1 then (select cde_nome from cde where cde_cod = pac_cid)\n        else pac_cid end as DS_CIDADE\n        ,pac_nome as DS_PESSOA_FISICA\n        ,cnv_cod as CD_CONVENIO\n        ,cnv_nome as DS_CONVENIO\n        ,psv_exe.psv_cod as CD_MEDICO_EXECUTOR\n        ,psv_exe.psv_apel as DS_MEDICO_EXECUTOR\n        ,psv_req.psv_cod as CD_MEDICO_REQUISITANTE\n        ,psv_req.psv_apel as DS_MEDICO_REQUISITANTE\n        ,isnull(tab_padrao,0) as IE_ORIGEM_PROCEDIMENTO\n        ,smm_cod as CD_PROCEDIMENTO\n        ,smk_rot as DS_PROCEDIMENTO\n        ,case ctf_categ \n            when 'C' then 'Consulta'\n            when 'E' then 'Exames'\n            when 'R' then 'Cirurgia'\n            when 'T' then 'Taxas'\n            when 'A' then 'Terapia'\n            when 'O' then 'Outras'\n            when 'M' then 'Materiais'\n            when 'S' then 'Materiais Especiais'\n            when 'N' then 'Medicamentos'\n            when 'G' then 'Gases'\n            when 'O' then 'Outros'\n        end as DS_CLASSIFICACAO\n        ,smm_qt as QT_PROCEDIMENTO\n        ,smm_vlr + isnull(smm_ajuste_vlr,0) as VL_PROCEDIMENTO\n        ,case \n            when smm_fat_serie is not null then 2\n        else 1 end AS IE_STATUS_ACERTO\n        ,case \n            when smm_fat_serie is not null then 'Definitivo'\n        else 'Provisório' end as STATUS_CONTA\n        ,0 as CD_TUSS,\n        0 as NR_SEQ_PROC_INTERNO\n    from \n        osm\n        inner join smm on (smm_osm_serie = osm_serie and smm_osm = osm_num)\n        inner join str str_osm on (str_osm.str_cod = osm_str)\n        inner join str str_emp on (str_osm.str_str_cod = str_emp.str_cod)\n        inner join pac on (pac_reg = osm_pac)\n        inner join cnv on (cnv_cod = osm_cnv)\n        inner join psv psv_exe on (psv_exe.psv_cod = smm_med)\n        inner join psv psv_req on (psv_req.psv_cod = smm_med)\n        inner join smk on (smk_cod = smm_cod and smk_tipo = smm_tpcod)\n        inner join ctf on (ctf_cod = smk_ctf and ctf_tipo = smk_tipo)\n        \n        inner join emp ON (emp_cod = str_emp.str_emp_cod)\n        inner join gcc ON (gcc_str_cod = str_emp.str_cod)\n\n        left outer join tab on (tab_cod = smm_tab_cod)\n        \n    where \n        1 = 1\n        and convert(varchar(10), osm_dthr, 103) = convert(varchar(10), getdate(), 103)\nand osm_dthr between GETDATE() - 730 and GETDATE()",
								"queryTimeout": "02:00:00",
								"partitionOption": "None"
							},
							"sink": {
								"type": "AzureSqlSink"
							},
							"enableStaging": false
						},
						"inputs": [
							{
								"referenceName": "SMART_IOF_PrdDataSet",
								"type": "DatasetReference",
								"parameters": {}
							}
						],
						"outputs": [
							{
								"referenceName": "AZ_SQL_TB_Unidade_Producao_Medica",
								"type": "DatasetReference",
								"parameters": {}
							}
						]
					},
					{
						"name": "Convenios",
						"type": "Copy",
						"dependsOn": [
							{
								"activity": "Wait1",
								"dependencyConditions": [
									"Succeeded"
								]
							}
						],
						"policy": {
							"timeout": "7.00:00:00",
							"retry": 0,
							"retryIntervalInSeconds": 30,
							"secureOutput": false,
							"secureInput": false
						},
						"userProperties": [],
						"typeProperties": {
							"source": {
								"type": "SqlServerSource",
								"sqlReaderQuery": "select cnv_cod AS CD_CONVENIO, cnv.cnv_nome AS DS_CONVENIO, gcc.gcc_cod AS CD_ESTABELECIMENTO, emp.emp_cgc AS CNPJ\nfrom cnv,\n     gcc,\n     str,\n     emp\nwhere gcc.gcc_str_cod = str_cod\nand str_emp_cod = emp_cod\nand emp_cgc <> '-'\nand cnv_cod <> '999'\nand cnv_stat = 'A'",
								"queryTimeout": "02:00:00",
								"partitionOption": "None"
							},
							"sink": {
								"type": "AzureSqlSink"
							},
							"enableStaging": false
						},
						"inputs": [
							{
								"referenceName": "SMART_IOF_PrdDataSet",
								"type": "DatasetReference",
								"parameters": {}
							}
						],
						"outputs": [
							{
								"referenceName": "AZ_SQL_TB_Convenio",
								"type": "DatasetReference",
								"parameters": {}
							}
						]
					},
					{
						"name": "Setor",
						"type": "Copy",
						"dependsOn": [
							{
								"activity": "Wait1",
								"dependencyConditions": [
									"Succeeded"
								]
							}
						],
						"policy": {
							"timeout": "7.00:00:00",
							"retry": 0,
							"retryIntervalInSeconds": 30,
							"secureOutput": false,
							"secureInput": false
						},
						"userProperties": [],
						"typeProperties": {
							"source": {
								"type": "SqlServerSource",
								"sqlReaderQuery": "SELECT STR_COD AS CD_SETOR_ATENDIMENTO, \nSTR_NOME AS DS_SETOR_ATENDIMENTO, \nEMP_CGC AS CNPJ\nFROM STR, EMP\nWHERE STR_EMP_COD = EMP_COD\nAND EMP_CGC <> '-'\nAND STR_COD <> '999'",
								"queryTimeout": "02:00:00",
								"partitionOption": "None"
							},
							"sink": {
								"type": "AzureSqlSink"
							},
							"enableStaging": false
						},
						"inputs": [
							{
								"referenceName": "SMART_IOF_PrdDataSet",
								"type": "DatasetReference",
								"parameters": {}
							}
						],
						"outputs": [
							{
								"referenceName": "AZ_SQL_TB_Setor",
								"type": "DatasetReference",
								"parameters": {}
							}
						]
					},
					{
						"name": "Execute Itabuna",
						"type": "ExecutePipeline",
						"dependsOn": [
							{
								"activity": "Producao Procedimentos IOF",
								"dependencyConditions": [
									"Succeeded"
								]
							},
							{
								"activity": "Convenios",
								"dependencyConditions": [
									"Succeeded"
								]
							},
							{
								"activity": "Setor",
								"dependencyConditions": [
									"Succeeded"
								]
							}
						],
						"userProperties": [],
						"typeProperties": {
							"pipeline": {
								"referenceName": "Producao Medica Itabuna",
								"type": "PipelineReference"
							},
							"waitOnCompletion": true,
							"parameters": {}
						}
					}
				],
				"folder": {
					"name": "Produção Médica CSI"
				},
				"annotations": []
			},
			"dependsOn": [
				"[concat(variables('factoryId'), '/pipelines/Producao Medica Itabuna')]"
			]
		},
		{
			"name": "[concat(parameters('factoryName'), '/Geral Atendimentos DAYHORC')]",
			"type": "Microsoft.DataFactory/factories/pipelines",
			"apiVersion": "2018-06-01",
			"properties": {
				"description": "Alimenta as informações das tabelas:\n\nAtendimento_ Unidade \nAgendamento_Unidade\nUsuarios_Unidade\nConsultas_Unidade\nAgendas Unidade\n\nPara extração de relatórios do call center.",
				"activities": [
					{
						"name": "Wait",
						"type": "Wait",
						"dependsOn": [],
						"userProperties": [],
						"typeProperties": {
							"waitTimeInSeconds": 1
						}
					},
					{
						"name": "Atendimento DH",
						"type": "Copy",
						"dependsOn": [
							{
								"activity": "Wait",
								"dependencyConditions": [
									"Succeeded"
								]
							}
						],
						"policy": {
							"timeout": "7.00:00:00",
							"retry": 0,
							"retryIntervalInSeconds": 30,
							"secureOutput": false,
							"secureInput": false
						},
						"userProperties": [],
						"typeProperties": {
							"source": {
								"type": "SqlServerSource",
								"sqlReaderQuery": "SELECT DISTINCT pac_reg AS CD_PESSOA_FISICA\n    , rtrim(ltrim(pac_nome)) AS NM_PESSOA_FISICA\n    , convert(CHAR(10), osm_dthr, 121) AS DT_ENTRADA\n    , LEFT(CONVERT(VARCHAR(12), osm_dthr, 114),8) AS HR_ENTRADA\n    , smm_med AS NM_MEDICO\n    , osm_cnv AS CD_CONVENIO\n    , cnv_nome AS DS_CONVENIO\n    , convert(VARCHAR, (convert(VARCHAR, osm_serie) + convert(VARCHAR, osm_num))) AS NR_ATENDIMENTO\n    , emp_cgc AS CNPJ\n    , emp_nome_fantasia AS DS_UNIDADE\n    , emp_nome_fantasia AS MARCA\n    , 0 AS CD_PROCEDENCIA\n    , 'NAO ENCONTRADO' AS DS_PROCEDENCIA\n    , 'NAO ENCONTRADO' AS ID\n    , CONVERT(INT, DAY(osm_dthr)) AS DIA\n    , CONVERT(INT, MONTH(osm_dthr)) AS MES\n    , CONVERT(INT, YEAR(osm_dthr)) AS ANO,\n'Smart DH Itaigara' as BASE\nFROM osm\nINNER JOIN smm\n    ON smm_osm_serie = osm_serie\n        AND smm_osm = osm_num\nINNER JOIN pac\n    ON pac_reg = osm_pac\nINNER JOIN cnv\n    ON osm_cnv = cnv_cod\nINNER JOIN str\n    ON str_cod = osm_str\nINNER JOIN psv\n    ON psv_cod = osm_mreq\nLEFT OUTER JOIN str str_e\n    ON str.str_str_cod = str_e.str_cod\nLEFT OUTER JOIN emp\n    ON str_e.str_emp_cod = emp_cod\nWHERE 1 = 1\n    AND (\n        smm_pacote IS NULL\n        OR (smm_pacote = 'C')\n        )\n    AND smm_sfat NOT IN ('C')\n\nAND osm_dthr BETWEEN GETDATE() - 730 AND GETDATE()",
								"queryTimeout": "02:00:00",
								"partitionOption": "None"
							},
							"sink": {
								"type": "AzureSqlSink"
							},
							"enableStaging": false
						},
						"inputs": [
							{
								"referenceName": "SMART_ITAIGARA_PrdDataSet",
								"type": "DatasetReference",
								"parameters": {}
							}
						],
						"outputs": [
							{
								"referenceName": "AZ_SQL_TB_Atendimento",
								"type": "DatasetReference",
								"parameters": {}
							}
						]
					},
					{
						"name": "Agendamentos DH",
						"type": "Copy",
						"dependsOn": [
							{
								"activity": "Wait",
								"dependencyConditions": [
									"Succeeded"
								]
							}
						],
						"policy": {
							"timeout": "7.00:00:00",
							"retry": 0,
							"retryIntervalInSeconds": 30,
							"secureOutput": false,
							"secureInput": false
						},
						"userProperties": [],
						"typeProperties": {
							"source": {
								"type": "SqlServerSource",
								"sqlReaderQuery": "SELECT DISTINCT AGM_PAC AS CD_PESSOA_FISICA\n    , agm.agm_cnv_cod AS CD_CONVENIO\n    , emp_cgc AS CNPJ\n    , CONVERT(DATE, AGM_HINI) AS DATA_AGENDA\n    , LEFT(CONVERT(VARCHAR(12), agm_hini, 114), 8) AS HORA_AGENDA\n    , CASE AGM_ATEND\n        WHEN 'CRG'\n            THEN 'Cirurgia'\n        WHEN 'ASS'\n            THEN 'Consulta'\n        when '' then 'Consulta'\n        ELSE 'Outros'\n        END AS TIPO_AGENDA\n    , pac.PAC_NOME AS NM_PACIENTE\n    , smk.smk_nome AS DS_PROCEDIMENTO_PRINC\n    , ' ' DS_PROCEDIMENTO_ADIC\n    , 1 AS IE_QUANTIDADE\n    , USR_NOME AS NM_USUARIO\n    , psv_nome AS NM_MEDICO\n    , EMP_NOME_FANTASIA AS DS_UNIDADE\n    , EMP_NOME_FANTASIA AS MARCA\n    , CASE \n        WHEN AGM_STAT = 'A'\n            THEN 'Aberta'\n        WHEN AGM_STAT = 'E'\n            THEN 'Executada'\n        WHEN AGM_STAT = 'C'\n            THEN 'Cancelada'\n        WHEN AGM_STAT = 'B'\n            THEN 'Bloqueada'\n        END STATUS_AGENDA\n    , CONVERT(VARCHAR, convert(VARCHAR, AGM_OSM_SERIE) + convert(VARCHAR, AGM_OSM_NUM)) AS NR_ATENDIMENTO\n    , AGM_num AS NR_SEQUENCIA\n    , '' ID\n    , '' AS CD_PROCEDENCIA\n    , agm_proc AS DS_PROCEDENCIA\n    , agm.AGM_DTMRC AS DT_AGENDAMENTO\n    , CONVERT(INT, DAY(AGM_HINI)) AS DIA\n    , CONVERT(INT, MONTH(AGM_HINI)) AS MES\n    , CONVERT(INT, YEAR(AGM_HINI)) AS ANO\n    , ' ' DS_CLASSIFICACAO\n    , ' ' DS_AGRUPAMENTO\n    , agm.AGM_CANC_MOT_COD AS CD_MOTIVO_CANCELAMENTO\n    , agm.AGM_CANC_MOT_TIPO AS DS_MOTIVO_CANCELAMENTO\n    , agm_med AS CD_AGENDA,\n'Smart DH Itaigara' as BASE\nFROM agm\nINNER JOIN usr\n    ON (agm.agm_usr_login = usr.usr_login)\nINNER JOIN psv\n    ON (psv.psv_cod = agm.agm_med)\nINNER JOIN smk\n    ON (\n            agm_smk = smk_cod\n            AND agm_tpsmk = smk_tipo\n            )\nINNER JOIN pac\n    ON (pac_reg = agm_pac)\nINNER JOIN loc\n    ON (AGM_LOC = LOC_COD)\nINNER JOIN str\n    ON (LOC_STR = STR.STR_COD)\nINNER JOIN str str_e\n    ON (STR.STR_STR_COD = STR_E.STR_COD)\nINNER JOIN cnv\n    ON (CNV_COD = AGM_CNV_COD)\nLEFT OUTER JOIN ctf ct1\n    ON (\n            ct1.ctf_cod = smk_ctf\n            AND ct1.ctf_tipo = smk_tipo\n            )\nLEFT OUTER JOIN emp\n    ON emp_cod = str_e.str_emp_cod\n\nWHERE AGM_DTMRC BETWEEN GETDATE() - 730 AND GETDATE()",
								"queryTimeout": "02:00:00",
								"partitionOption": "None"
							},
							"sink": {
								"type": "AzureSqlSink"
							},
							"enableStaging": false
						},
						"inputs": [
							{
								"referenceName": "SMART_ITAIGARA_PrdDataSet",
								"type": "DatasetReference",
								"parameters": {}
							}
						],
						"outputs": [
							{
								"referenceName": "AZ_SQL_TB_Agendamento",
								"type": "DatasetReference",
								"parameters": {}
							}
						]
					},
					{
						"name": "Usuarios DH",
						"type": "Copy",
						"dependsOn": [
							{
								"activity": "Wait",
								"dependencyConditions": [
									"Succeeded"
								]
							}
						],
						"policy": {
							"timeout": "7.00:00:00",
							"retry": 0,
							"retryIntervalInSeconds": 30,
							"secureOutput": false,
							"secureInput": false
						},
						"userProperties": [],
						"typeProperties": {
							"source": {
								"type": "SqlServerSource",
								"sqlReaderQuery": "select\nusr_login as NM_USUARIO,\nusr_nome as DS_USUARIO,\nusr_status as IE_SITUACAO,\nusr_dt_alter_senha as DT_ATUALIZACAO,\n'DAYHORC -  UNIDADE ITAIGARA' AS DS_UNIDADE,\n'13188370000227' as CNPJ,\n'DH' as MARCA,\n'Smart DH Itaigara' as BASE\nfrom usr",
								"queryTimeout": "02:00:00",
								"partitionOption": "None"
							},
							"sink": {
								"type": "AzureSqlSink"
							},
							"enableStaging": false
						},
						"inputs": [
							{
								"referenceName": "SMART_ITAIGARA_PrdDataSet",
								"type": "DatasetReference",
								"parameters": {}
							}
						],
						"outputs": [
							{
								"referenceName": "AZ_SQL_TB_Usuario",
								"type": "DatasetReference",
								"parameters": {}
							}
						]
					},
					{
						"name": "Consulta DH",
						"type": "Copy",
						"dependsOn": [
							{
								"activity": "Wait",
								"dependencyConditions": [
									"Succeeded"
								]
							}
						],
						"policy": {
							"timeout": "7.00:00:00",
							"retry": 0,
							"retryIntervalInSeconds": 30,
							"secureOutput": false,
							"secureInput": false
						},
						"userProperties": [],
						"typeProperties": {
							"source": {
								"type": "SqlServerSource",
								"sqlReaderQuery": "SELECT\nRCL_SMM AS NR_SEQUENCIA,\nCONVERT(DATE,RCL_DTHR_ATUAL) AS DT_ATUALIZACAO,\nCONVERT(VARCHAR,RCL_DTHR_ATUAL,108) as HR_ATUALIZACAO,\n\nCONVERT(VARCHAR,CONVERT(VARCHAR,RCL_OSM_SERIE) + CONVERT(VARCHAR,RCL_OSM)) AS NR_ATENDIMENTO, \n\nRCL_MED AS CD_MEDICO,\nPSV_APEL AS NM_MEDICO,\n'' AS DS_RETORNO,\nCONVERT(VARCHAR,RCL_LAUDO_RTF) AS DS_CONDUTA,\nRCL_PAC AS CD_PESSOA_FISICA,\nCONVERT(VARCHAR,RCL_TXT) AS DS_DIAGNOSTICO,\n'DAYHORC -  UNIDADE ITAIGARA' AS DS_UNIDADE,\n'13188370000227' as CNPJ,\n'DH' AS MARCA,\n'Smart DH Itaigara' as BASE\nFROM RCL\nINNER JOIN PSV ON PSV_COD = RCL_MED\n\nWHERE RCL_DTHR_ATUAL BETWEEN GETDATE() - 730 AND GETDATE()",
								"queryTimeout": "02:00:00",
								"partitionOption": "None"
							},
							"sink": {
								"type": "AzureSqlSink"
							},
							"enableStaging": false
						},
						"inputs": [
							{
								"referenceName": "SMART_ITAIGARA_PrdDataSet",
								"type": "DatasetReference",
								"parameters": {}
							}
						],
						"outputs": [
							{
								"referenceName": "AZ_SQL_TB_Consulta",
								"type": "DatasetReference",
								"parameters": {}
							}
						]
					},
					{
						"name": "Agendas DH",
						"type": "Copy",
						"dependsOn": [
							{
								"activity": "Wait",
								"dependencyConditions": [
									"Succeeded"
								]
							}
						],
						"policy": {
							"timeout": "7.00:00:00",
							"retry": 0,
							"retryIntervalInSeconds": 30,
							"secureOutput": false,
							"secureInput": false
						},
						"userProperties": [],
						"typeProperties": {
							"source": {
								"type": "SqlServerSource",
								"sqlReaderQuery": "SELECT distinct agd_med AS CD_AGENDA \n    , 0 AS DS_AGENDA\n    , 0 CD_TIPO_AGENDA\n    , psv_cod AS CD_PESSOA_FISICA\n    , emp_cgc AS CNPJ\n    , '' AS DS_AREA_ATUACAO\n    , 'A' AS IE_SITUACAO,\n    'Smart DH Itaigara' as BASE\n    -- , CASE \n    --     WHEN (agd_dt_reconstr IS not NULL and AGD_DT_GERA is not null)\n    --         THEN agd_dt_reconstr\n    --     WHEN (agd_dt_reconstr IS NULL and AGD_DT_GERA is not null)\n    --         THEN agd_dt_gera\n    --     ELSE AGD_DT_GERA\n    --     END AS DT_ATUALIZACAO\nFROM agd\nINNER JOIN PSV\n    ON agd_med = psv_cod\nINNER JOIN loc\n    ON loc_cod = agd_loc\nINNER JOIN str\n    ON str_cod = loc_str\nLEFT OUTER JOIN str str_e\n    ON str_e.str_cod = str.str_str_cod\nLEFT OUTER JOIN emp\n    ON emp_cod = str_e.str_emp_cod",
								"queryTimeout": "02:00:00",
								"partitionOption": "None"
							},
							"sink": {
								"type": "AzureSqlSink"
							},
							"enableStaging": false
						},
						"inputs": [
							{
								"referenceName": "SMART_ITAIGARA_PrdDataSet",
								"type": "DatasetReference",
								"parameters": {}
							}
						],
						"outputs": [
							{
								"referenceName": "AZ_SQL_TB_Agenda",
								"type": "DatasetReference",
								"parameters": {}
							}
						]
					},
					{
						"name": "Execute Pipeline HOSL",
						"type": "ExecutePipeline",
						"dependsOn": [
							{
								"activity": "Atendimento DH",
								"dependencyConditions": [
									"Succeeded"
								]
							},
							{
								"activity": "Agendamentos DH",
								"dependencyConditions": [
									"Succeeded"
								]
							},
							{
								"activity": "Usuarios DH",
								"dependencyConditions": [
									"Succeeded"
								]
							},
							{
								"activity": "Consulta DH",
								"dependencyConditions": [
									"Succeeded"
								]
							},
							{
								"activity": "Agendas DH",
								"dependencyConditions": [
									"Succeeded"
								]
							}
						],
						"userProperties": [],
						"typeProperties": {
							"pipeline": {
								"referenceName": "Geral Atendimentos HOSL",
								"type": "PipelineReference"
							},
							"waitOnCompletion": true,
							"parameters": {}
						}
					}
				],
				"folder": {
					"name": "Atendimento"
				},
				"annotations": []
			},
			"dependsOn": [
				"[concat(variables('factoryId'), '/pipelines/Geral Atendimentos HOSL')]"
			]
		},
		{
			"name": "[concat(parameters('factoryName'), '/Producao Medica INOB')]",
			"type": "Microsoft.DataFactory/factories/pipelines",
			"apiVersion": "2018-06-01",
			"properties": {
				"description": "Pipeline desenvolvido para extração de informações de produção medica das unidades com o sistema Tasy e Smart.",
				"activities": [
					{
						"name": "Wait1",
						"type": "Wait",
						"dependsOn": [],
						"userProperties": [],
						"typeProperties": {
							"waitTimeInSeconds": 1
						}
					},
					{
						"name": "Producao Procedimentos INOB",
						"type": "Copy",
						"dependsOn": [
							{
								"activity": "Wait1",
								"dependencyConditions": [
									"Succeeded"
								]
							}
						],
						"policy": {
							"timeout": "7.00:00:00",
							"retry": 0,
							"retryIntervalInSeconds": 30,
							"secureOutput": false,
							"secureInput": false
						},
						"userProperties": [],
						"typeProperties": {
							"source": {
								"type": "SqlServerSource",
								"sqlReaderQuery": " select\n        'INOB' as BASE\n        ,EMP_CGC as CNPJ\n        ,gcc_descr as MARCA\n        ,smm_dthr_alter as DT_ATUALIZACAO\n        ,convert(varchar,osm_serie) + convert(varchar,osm_num) as NR_ATENDIMENTO --duvida\n        ,osm_dthr as DT_ENTRADA\n        ,convert(varchar,osm_serie) + convert(varchar,osm_num) as NR_INTERNO_CONTA --duvida\n        ,osm_pac as CD_PESSOA_FISICA\n        ,pac_nasc as DT_NASCIMENTO\n        ,pac_numcpf as NR_CPF\n        ,pac_sexo as IE_SEXO\n        ,pac_cep as NR_CEP\n        ,case when isnumeric(pac_cid) = 1 then (select cde_nome from cde where cde_cod = pac_cid)\n        else pac_cid end as DS_CIDADE\n        ,pac_nome as DS_PESSOA_FISICA\n        ,cnv_cod as CD_CONVENIO\n        ,cnv_nome as DS_CONVENIO\n        ,psv_exe.psv_cod as CD_MEDICO_EXECUTOR\n        ,psv_exe.psv_apel as DS_MEDICO_EXECUTOR\n        ,psv_req.psv_cod as CD_MEDICO_REQUISITANTE\n        ,psv_req.psv_apel as DS_MEDICO_REQUISITANTE\n        ,isnull(tab_padrao,0) as IE_ORIGEM_PROCEDIMENTO\n        ,smm_cod as CD_PROCEDIMENTO\n        ,smk_rot as DS_PROCEDIMENTO\n        ,case ctf_categ \n            when 'C' then 'Consulta'\n            when 'E' then 'Exames'\n            when 'R' then 'Cirurgia'\n            when 'T' then 'Taxas'\n            when 'A' then 'Terapia'\n            when 'O' then 'Outras'\n            when 'M' then 'Materiais'\n            when 'S' then 'Materiais Especiais'\n            when 'N' then 'Medicamentos'\n            when 'G' then 'Gases'\n            when 'O' then 'Outros'\n        end as DS_CLASSIFICACAO\n        ,smm_qt as QT_PROCEDIMENTO\n        ,smm_vlr + isnull(smm_ajuste_vlr,0) as VL_PROCEDIMENTO\n        ,case \n            when smm_fat_serie is not null then 2\n        else 1 end AS IE_STATUS_ACERTO\n        ,case \n            when smm_fat_serie is not null then 'Definitivo'\n        else 'Provisório' end as STATUS_CONTA\n        ,0 as CD_TUSS,\n        0 as NR_SEQ_PROC_INTERNO\n    from \n        osm\n        inner join smm on (smm_osm_serie = osm_serie and smm_osm = osm_num)\n        inner join str str_osm on (str_osm.str_cod = osm_str)\n        inner join str str_emp on (str_osm.str_str_cod = str_emp.str_cod)\n        inner join pac on (pac_reg = osm_pac)inner join cnv on (cnv_cod = osm_cnv)\n        inner join psv psv_exe on (psv_exe.psv_cod = smm_med)\n        inner join psv psv_req on (psv_req.psv_cod = smm_med)\n        inner join smk on (smk_cod = smm_cod and smk_tipo = smm_tpcod)\n        inner join gcc on (str_emp.str_cod = gcc_cod)\n        \n        inner join emp ON (emp_cod = str_emp.str_emp_cod)\n\n        inner join ctf on (ctf_cod = smk_ctf and ctf_tipo = smk_tipo)\n        left outer join tab on (tab_cod = smm_tab_cod)\n    where \n        1 = 1\n        --and convert(varchar(10), osm_dthr, 103) = convert(varchar(10), getdate(), 103)\nand osm_dthr between GETDATE() - 730 and GETDATE()",
								"queryTimeout": "02:00:00",
								"partitionOption": "None"
							},
							"sink": {
								"type": "AzureSqlSink"
							},
							"enableStaging": false
						},
						"inputs": [
							{
								"referenceName": "SMART_INOB_PrdDataSet",
								"type": "DatasetReference",
								"parameters": {}
							}
						],
						"outputs": [
							{
								"referenceName": "AZ_SQL_TB_Unidade_Producao_Medica",
								"type": "DatasetReference",
								"parameters": {}
							}
						]
					},
					{
						"name": "Convenios",
						"type": "Copy",
						"dependsOn": [
							{
								"activity": "Wait1",
								"dependencyConditions": [
									"Succeeded"
								]
							}
						],
						"policy": {
							"timeout": "7.00:00:00",
							"retry": 0,
							"retryIntervalInSeconds": 30,
							"secureOutput": false,
							"secureInput": false
						},
						"userProperties": [],
						"typeProperties": {
							"source": {
								"type": "SqlServerSource",
								"sqlReaderQuery": "select cnv_cod AS CD_CONVENIO, cnv.cnv_nome AS DS_CONVENIO, gcc.gcc_cod AS CD_ESTABELECIMENTO, emp.emp_cgc AS CNPJ\nfrom cnv,\n     gcc,\n     str,\n     emp\nwhere gcc.gcc_str_cod = str_cod\nand str_emp_cod = emp_cod\nand emp_cgc <> '-'\nand cnv_cod <> '999'\nand cnv_stat = 'A'",
								"queryTimeout": "02:00:00",
								"partitionOption": "None"
							},
							"sink": {
								"type": "AzureSqlSink"
							},
							"enableStaging": false
						},
						"inputs": [
							{
								"referenceName": "SMART_INOB_PrdDataSet",
								"type": "DatasetReference",
								"parameters": {}
							}
						],
						"outputs": [
							{
								"referenceName": "AZ_SQL_TB_Convenio",
								"type": "DatasetReference",
								"parameters": {}
							}
						]
					},
					{
						"name": "Setor",
						"type": "Copy",
						"dependsOn": [
							{
								"activity": "Wait1",
								"dependencyConditions": [
									"Succeeded"
								]
							}
						],
						"policy": {
							"timeout": "7.00:00:00",
							"retry": 0,
							"retryIntervalInSeconds": 30,
							"secureOutput": false,
							"secureInput": false
						},
						"userProperties": [],
						"typeProperties": {
							"source": {
								"type": "SqlServerSource",
								"sqlReaderQuery": "SELECT STR_COD AS CD_SETOR_ATENDIMENTO, \nSTR_NOME AS DS_SETOR_ATENDIMENTO, \nEMP_CGC AS CNPJ\nFROM STR, EMP\nWHERE STR_EMP_COD = EMP_COD\nAND EMP_CGC <> '-'\nAND STR_COD <> '999'",
								"queryTimeout": "02:00:00",
								"partitionOption": "None"
							},
							"sink": {
								"type": "AzureSqlSink"
							},
							"enableStaging": false
						},
						"inputs": [
							{
								"referenceName": "SMART_INOB_PrdDataSet",
								"type": "DatasetReference",
								"parameters": {}
							}
						],
						"outputs": [
							{
								"referenceName": "AZ_SQL_TB_Setor",
								"type": "DatasetReference",
								"parameters": {}
							}
						]
					},
					{
						"name": "Execute IOF",
						"type": "ExecutePipeline",
						"dependsOn": [
							{
								"activity": "Producao Procedimentos INOB",
								"dependencyConditions": [
									"Succeeded"
								]
							},
							{
								"activity": "Convenios",
								"dependencyConditions": [
									"Succeeded"
								]
							},
							{
								"activity": "Setor",
								"dependencyConditions": [
									"Succeeded"
								]
							}
						],
						"userProperties": [],
						"typeProperties": {
							"pipeline": {
								"referenceName": "Producao Medica IOF",
								"type": "PipelineReference"
							},
							"waitOnCompletion": true,
							"parameters": {}
						}
					}
				],
				"folder": {
					"name": "Produção Médica CSI"
				},
				"annotations": []
			},
			"dependsOn": [
				"[concat(variables('factoryId'), '/pipelines/Producao Medica IOF')]"
			]
		},
		{
			"name": "[concat(parameters('factoryName'), '/Producao Medica HOSL')]",
			"type": "Microsoft.DataFactory/factories/pipelines",
			"apiVersion": "2018-06-01",
			"properties": {
				"description": "Pipeline desenvolvido para extração de informações de produção medica das unidades com o sistema Tasy e Smart.",
				"activities": [
					{
						"name": "Wait1",
						"type": "Wait",
						"dependsOn": [],
						"userProperties": [],
						"typeProperties": {
							"waitTimeInSeconds": 1
						}
					},
					{
						"name": "Producao Procedimentos HOSL",
						"type": "Copy",
						"dependsOn": [
							{
								"activity": "Wait1",
								"dependencyConditions": [
									"Succeeded"
								]
							}
						],
						"policy": {
							"timeout": "7.00:00:00",
							"retry": 0,
							"retryIntervalInSeconds": 30,
							"secureOutput": false,
							"secureInput": false
						},
						"userProperties": [],
						"typeProperties": {
							"source": {
								"type": "SqlServerSource",
								"sqlReaderQuery": "    select\n        'Smart HOSL' as BASE\n        ,EMP_CGC as CNPJ\n        ,gcc_descr as MARCA\n        ,smm_dthr_alter as DT_ATUALIZACAO \n        ,convert(varchar,osm_serie) + convert(varchar,osm_num) as NR_ATENDIMENTO --duvida\n        ,osm_dthr as DT_ENTRADA\n        ,convert(varchar,osm_serie) + convert(varchar,osm_num) as NR_INTERNO_CONTA --duvida\n        ,osm_pac as CD_PESSOA_FISICA\n        ,pac_nasc as DT_NASCIMENTO\n        ,pac_numcpf as NR_CPF\n        ,pac_sexo as IE_SEXO\n        ,pac_cep as NR_CEP\n        ,case when isnumeric(pac_cid) = 1 then (select cde_nome from cde where cde_cod = pac_cid)\n        else pac_cid end as DS_CIDADE\n        ,pac_nome as DS_PESSOA_FISICA\n        ,cnv_cod as CD_CONVENIO\n        ,cnv_nome as DS_CONVENIO\n        ,psv_exe.psv_cod as CD_MEDICO_EXECUTOR\n        ,psv_exe.psv_apel as DS_MEDICO_EXECUTOR\n        ,psv_req.psv_cod as CD_MEDICO_REQUISITANTE\n        ,psv_req.psv_apel as DS_MEDICO_REQUISITANTE\n        ,isnull(tab_padrao,0) as IE_ORIGEM_PROCEDIMENTO\n        ,smm_cod as CD_PROCEDIMENTO\n        ,smk_rot as DS_PROCEDIMENTO\n        ,case ctf_categ \n            when 'C' then 'Consulta'\n            when 'E' then 'Exames'\n            when 'R' then 'Cirurgia'\n            when 'T' then 'Taxas'\n            when 'A' then 'Terapia'\n            when 'O' then 'Outras'\n            when 'M' then 'Materiais'\n            when 'S' then 'Materiais Especiais'\n            when 'N' then 'Medicamentos'\n            when 'G' then 'Gases'\n            when 'O' then 'Outros'\n        end as DS_CLASSIFICACAO\n        ,smm_qt as QT_PROCEDIMENTO\n        ,smm_vlr + isnull(smm_ajuste_vlr,0) as VL_PROCEDIMENTO\n        ,case \n            when smm_fat_serie is not null then 2\n        else 1 end AS IE_STATUS_ACERTO\n        ,case \n            when smm_fat_serie is not null then 'Definitivo'\n        else 'Provisório' end as STATUS_CONTA\n        ,0 as CD_TUSS,\n        0 as NR_SEQ_PROC_INTERNO\n    from \n        osm\n        inner join smm on (smm_osm_serie = osm_serie and smm_osm = osm_num)\n        inner join str str_osm on (str_osm.str_cod = osm_str)\n        inner join str str_emp on (str_osm.str_str_cod = str_emp.str_cod)\n        inner join pac on (pac_reg = osm_pac)inner join cnv on (cnv_cod = osm_cnv)\n        inner join psv psv_exe on (psv_exe.psv_cod = smm_med)\n        inner join psv psv_req on (psv_req.psv_cod = smm_med)\n        inner join smk on (smk_cod = smm_cod and smk_tipo = smm_tpcod)\n        inner join gcc on (str_emp.str_cod = gcc_cod)\n        \n        inner join emp ON (emp_cod = str_emp.str_emp_cod)\n\n        inner join ctf on (ctf_cod = smk_ctf and ctf_tipo = smk_tipo)\n        left outer join tab on (tab_cod = smm_tab_cod)\n    where \n        1 = 1\n        and convert(varchar(10), osm_dthr, 103) = convert(varchar(10), getdate(), 103)\nand osm_dthr between GETDATE() - 730 and GETDATE()",
								"queryTimeout": "02:00:00",
								"partitionOption": "None"
							},
							"sink": {
								"type": "AzureSqlSink"
							},
							"enableStaging": false
						},
						"inputs": [
							{
								"referenceName": "SMART_HOSL_PrdDataSet",
								"type": "DatasetReference",
								"parameters": {}
							}
						],
						"outputs": [
							{
								"referenceName": "AZ_SQL_TB_Unidade_Producao_Medica",
								"type": "DatasetReference",
								"parameters": {}
							}
						]
					},
					{
						"name": "Convenios",
						"type": "Copy",
						"dependsOn": [
							{
								"activity": "Wait1",
								"dependencyConditions": [
									"Succeeded"
								]
							}
						],
						"policy": {
							"timeout": "7.00:00:00",
							"retry": 0,
							"retryIntervalInSeconds": 30,
							"secureOutput": false,
							"secureInput": false
						},
						"userProperties": [],
						"typeProperties": {
							"source": {
								"type": "SqlServerSource",
								"sqlReaderQuery": "select cnv_cod AS CD_CONVENIO, cnv.cnv_nome AS DS_CONVENIO, gcc.gcc_cod AS CD_ESTABELECIMENTO, emp.emp_cgc AS CNPJ\nfrom cnv,\n     gcc,\n     str,\n     emp\nwhere gcc.gcc_str_cod = str_cod\nand str_emp_cod = emp_cod\nand emp_cgc <> '-'\nand cnv_cod <> '999'\nand cnv_stat = 'A'",
								"queryTimeout": "02:00:00",
								"partitionOption": "None"
							},
							"sink": {
								"type": "AzureSqlSink"
							},
							"enableStaging": false
						},
						"inputs": [
							{
								"referenceName": "SMART_HOSL_PrdDataSet",
								"type": "DatasetReference",
								"parameters": {}
							}
						],
						"outputs": [
							{
								"referenceName": "AZ_SQL_TB_Convenio",
								"type": "DatasetReference",
								"parameters": {}
							}
						]
					},
					{
						"name": "Setor",
						"type": "Copy",
						"dependsOn": [
							{
								"activity": "Wait1",
								"dependencyConditions": [
									"Succeeded"
								]
							}
						],
						"policy": {
							"timeout": "7.00:00:00",
							"retry": 0,
							"retryIntervalInSeconds": 30,
							"secureOutput": false,
							"secureInput": false
						},
						"userProperties": [],
						"typeProperties": {
							"source": {
								"type": "SqlServerSource",
								"sqlReaderQuery": "SELECT STR_COD AS CD_SETOR_ATENDIMENTO, \nSTR_NOME AS DS_SETOR_ATENDIMENTO, \nEMP_CGC AS CNPJ\nFROM STR, EMP\nWHERE STR_EMP_COD = EMP_COD\nAND EMP_CGC <> '-'\nAND STR_COD <> '999'",
								"queryTimeout": "02:00:00",
								"partitionOption": "None"
							},
							"sink": {
								"type": "AzureSqlSink"
							},
							"enableStaging": false
						},
						"inputs": [
							{
								"referenceName": "SMART_HOSL_PrdDataSet",
								"type": "DatasetReference",
								"parameters": {}
							}
						],
						"outputs": [
							{
								"referenceName": "AZ_SQL_TB_Setor",
								"type": "DatasetReference",
								"parameters": {}
							}
						]
					},
					{
						"name": "Execute INOB",
						"type": "ExecutePipeline",
						"dependsOn": [
							{
								"activity": "Producao Procedimentos HOSL",
								"dependencyConditions": [
									"Succeeded"
								]
							},
							{
								"activity": "Convenios",
								"dependencyConditions": [
									"Succeeded"
								]
							},
							{
								"activity": "Setor",
								"dependencyConditions": [
									"Succeeded"
								]
							}
						],
						"userProperties": [],
						"typeProperties": {
							"pipeline": {
								"referenceName": "Producao Medica INOB",
								"type": "PipelineReference"
							},
							"waitOnCompletion": true,
							"parameters": {}
						}
					}
				],
				"folder": {
					"name": "Produção Médica CSI"
				},
				"annotations": []
			},
			"dependsOn": [
				"[concat(variables('factoryId'), '/pipelines/Producao Medica INOB')]"
			]
		},
		{
			"name": "[concat(parameters('factoryName'), '/Producao Medica HOB')]",
			"type": "Microsoft.DataFactory/factories/pipelines",
			"apiVersion": "2018-06-01",
			"properties": {
				"description": "Pipeline desenvolvido para extração de informações de produção medica das unidades com o sistema Tasy e Smart.",
				"activities": [
					{
						"name": "Wait1",
						"type": "Wait",
						"dependsOn": [],
						"userProperties": [],
						"typeProperties": {
							"waitTimeInSeconds": 1
						}
					},
					{
						"name": "Producao Procedimentos HOB",
						"type": "Copy",
						"dependsOn": [
							{
								"activity": "Wait1",
								"dependencyConditions": [
									"Succeeded"
								]
							}
						],
						"policy": {
							"timeout": "7.00:00:00",
							"retry": 0,
							"retryIntervalInSeconds": 30,
							"secureOutput": false,
							"secureInput": false
						},
						"userProperties": [],
						"typeProperties": {
							"source": {
								"type": "OracleSource",
								"oracleReaderQuery": "select \n\n'Tasy HTML' as BASE,\ne.cd_cgc as CNPJ,\ne.nm_fantasia_estab as marca,\np.dt_atualizacao,\np.nr_atendimento,\nat.dt_entrada,\np.nr_interno_conta,\n--obter_nome_estab(c.cd_estabelecimento) as ds_estabelecimento,\npf.cd_pessoa_fisica,\npf.dt_nascimento,\npf.nr_cpf,\npf.ie_sexo,\nobter_compl_pf(pf.cd_pessoa_fisica,1,'CEP') as nr_cep,\nobter_compl_pf(pf.cd_pessoa_fisica,1,'CI') as ds_cidade,\nobter_nome_pf(at.cd_pessoa_fisica) as ds_pessoa_fisica,\np.cd_convenio as cd_convenio,\nobter_nome_convenio(c.cd_convenio_parametro) as ds_convenio,\np.cd_medico_executor,\nobter_nome_pf(p.cd_medico_executor) as ds_medico_executor,\np.cd_medico_req as cd_medico_requisitante,\nobter_nome_pf(p.cd_medico_req) as ds_medico_requisitante,\np.ie_origem_proced as ie_origem_procedimento,\np.cd_procedimento,\nobter_desc_procedimento(p.cd_procedimento, p.ie_origem_proced) as ds_procedimento, \nobter_valor_dominio(19,pr.ie_classificacao) as ds_classificacao,\np.qt_procedimento,\n--c.vl_conta,\np.vl_procedimento,\nc.ie_status_acerto,\ndecode(c.ie_status_acerto, 1,'Provisorio' , 2 ,'Definitivo') as status_conta,\n'' as cd_tuss,\np.nr_seq_proc_interno\nfrom procedimento_paciente p,\natendimento_paciente at,\npessoa_fisica pf,\nprocedimento pr,\nconta_paciente c,\nestabelecimento e,\nempresa em\nwhere p.nr_atendimento = at.nr_atendimento\nand at.cd_pessoa_fisica = pf.cd_pessoa_fisica\nand p.cd_procedimento = pr.cd_procedimento\nand p.ie_origem_proced = pr.ie_origem_proced\nand p.nr_interno_conta = c.nr_interno_conta\nand at.cd_estabelecimento = e.cd_estabelecimento\nand e.cd_empresa = em.cd_empresa\nand p.cd_motivo_exc_conta is null\nand c.ie_cancelamento is null\nand at.dt_entrada between sysdate - 730 and sysdate",
								"partitionOption": "None"
							},
							"sink": {
								"type": "AzureSqlSink"
							},
							"enableStaging": false
						},
						"inputs": [
							{
								"referenceName": "CloudTasyPrdDataSet",
								"type": "DatasetReference",
								"parameters": {}
							}
						],
						"outputs": [
							{
								"referenceName": "AZ_SQL_TB_Unidade_Producao_Medica",
								"type": "DatasetReference",
								"parameters": {}
							}
						]
					},
					{
						"name": "Producao Materiais HOB",
						"type": "Copy",
						"dependsOn": [
							{
								"activity": "Wait1",
								"dependencyConditions": [
									"Succeeded"
								]
							}
						],
						"policy": {
							"timeout": "7.00:00:00",
							"retry": 0,
							"retryIntervalInSeconds": 30,
							"secureOutput": false,
							"secureInput": false
						},
						"userProperties": [],
						"typeProperties": {
							"source": {
								"type": "OracleSource",
								"oracleReaderQuery": "select 'Tasy HTML' as BASE,\ne.cd_cgc as CNPJ,\ne.nm_fantasia_estab as marca,\nmp.dt_atualizacao,\nmp.nr_atendimento,\nat.dt_entrada,\nmp.nr_interno_conta,\npf.cd_pessoa_fisica,\npf.dt_nascimento,\npf.nr_cpf,\npf.ie_sexo,\nobter_compl_pf(pf.cd_pessoa_fisica,1,'CEP') as nr_cep,\nobter_compl_pf(pf.cd_pessoa_fisica,1,'CI') as ds_cidade,\nobter_nome_pf(at.cd_pessoa_fisica) as ds_pessoa_fisica,\nmp.cd_convenio as cd_convenio,\nobter_nome_convenio(c.cd_convenio_parametro) as ds_convenio,\nat.cd_medico_atendimento as cd_medico_executor,\nobter_nome_pf(at.cd_medico_atendimento) as ds_medico_executor,\nmp.cd_medico_prescritor as cd_medico_requisitante,\nobter_nome_pf(mp.cd_medico_prescritor) as ds_medico_requisitante,\n' ' ie_origem_procedimento,\nmp.cd_material as cd_procedimento,\nm.ds_material as ds_procedimento, \n'Material'  ds_classificacao,\nmp.qt_material as qt_procedimento,\nmp.vl_material as vl_procedimento,\nc.ie_status_acerto,\ndecode(c.ie_status_acerto, 1,'Provisorio' , 2 ,'Definitivo') as status_conta,\n'' as cd_tuss,\n0 as nr_seq_proc_interno\nfrom  conta_paciente c,\n      material_atend_paciente mp,\n      material m,\n      estabelecimento e,\n      atendimento_paciente at,\n      pessoa_fisica pf\nwhere c.nr_atendimento = mp.nr_atendimento\nand c.nr_interno_conta = mp.nr_interno_conta\nand mp.cd_material = m.cd_material\nand c.cd_estabelecimento = e.cd_estabelecimento\nand mp.nr_atendimento = at.nr_atendimento\nand at.cd_pessoa_fisica = pf.cd_pessoa_fisica\nand mp.dt_atualizacao between sysdate -730 and sysdate\nand mp.cd_motivo_exc_conta is null",
								"partitionOption": "None"
							},
							"sink": {
								"type": "AzureSqlSink"
							},
							"enableStaging": false
						},
						"inputs": [
							{
								"referenceName": "CloudTasyPrdDataSet",
								"type": "DatasetReference",
								"parameters": {}
							}
						],
						"outputs": [
							{
								"referenceName": "AZ_SQL_TB_Unidade_Producao_Medica",
								"type": "DatasetReference",
								"parameters": {}
							}
						]
					},
					{
						"name": "Convenios",
						"type": "Copy",
						"dependsOn": [
							{
								"activity": "Wait1",
								"dependencyConditions": [
									"Succeeded"
								]
							}
						],
						"policy": {
							"timeout": "7.00:00:00",
							"retry": 0,
							"retryIntervalInSeconds": 30,
							"secureOutput": false,
							"secureInput": false
						},
						"userProperties": [],
						"typeProperties": {
							"source": {
								"type": "OracleSource",
								"oracleReaderQuery": "select cn.cd_convenio, cn.ds_convenio, e.cd_estabelecimento, e.cd_cgc as cnpj\nfrom convenio cn,\n     convenio_estabelecimento ce,\n     estabelecimento e\nwhere cn.cd_convenio = ce.cd_convenio\nand ce.cd_estabelecimento = e.cd_estabelecimento\norder by 2",
								"partitionOption": "None"
							},
							"sink": {
								"type": "AzureSqlSink"
							},
							"enableStaging": false
						},
						"inputs": [
							{
								"referenceName": "CloudTasyPrdDataSet",
								"type": "DatasetReference",
								"parameters": {}
							}
						],
						"outputs": [
							{
								"referenceName": "AZ_SQL_TB_Convenio",
								"type": "DatasetReference",
								"parameters": {}
							}
						]
					},
					{
						"name": "Setor",
						"type": "Copy",
						"dependsOn": [
							{
								"activity": "Wait1",
								"dependencyConditions": [
									"Succeeded"
								]
							}
						],
						"policy": {
							"timeout": "7.00:00:00",
							"retry": 0,
							"retryIntervalInSeconds": 30,
							"secureOutput": false,
							"secureInput": false
						},
						"userProperties": [],
						"typeProperties": {
							"source": {
								"type": "OracleSource",
								"oracleReaderQuery": "select a.cd_setor_atendimento, a.ds_setor_atendimento, e.cd_cgc as cnpj\nfrom setor_atendimento a,\nestabelecimento e\nwhere a.cd_estabelecimento = e.cd_estabelecimento\nand e.ie_situacao = 'A'",
								"partitionOption": "None"
							},
							"sink": {
								"type": "AzureSqlSink"
							},
							"enableStaging": false
						},
						"inputs": [
							{
								"referenceName": "CloudTasyPrdDataSet",
								"type": "DatasetReference",
								"parameters": {}
							}
						],
						"outputs": [
							{
								"referenceName": "AZ_SQL_TB_Setor",
								"type": "DatasetReference",
								"parameters": {}
							}
						]
					},
					{
						"name": "Execute HOSL",
						"type": "ExecutePipeline",
						"dependsOn": [
							{
								"activity": "Producao Procedimentos HOB",
								"dependencyConditions": [
									"Succeeded"
								]
							},
							{
								"activity": "Producao Materiais HOB",
								"dependencyConditions": [
									"Succeeded"
								]
							},
							{
								"activity": "Convenios",
								"dependencyConditions": [
									"Succeeded"
								]
							},
							{
								"activity": "Setor",
								"dependencyConditions": [
									"Succeeded"
								]
							}
						],
						"userProperties": [],
						"typeProperties": {
							"pipeline": {
								"referenceName": "Producao Medica HOSL",
								"type": "PipelineReference"
							},
							"waitOnCompletion": true,
							"parameters": {}
						}
					}
				],
				"folder": {
					"name": "Produção Médica CSI"
				},
				"annotations": []
			},
			"dependsOn": [
				"[concat(variables('factoryId'), '/pipelines/Producao Medica HOSL')]"
			]
		}
	]
}